destripegui/__init__.py
destripegui/destripegui.py
destripegui/data/DestripeGUI.exe
destripegui/data/config.ini
destripegui/data/lct.ico
destripegui/destripe/__init__.py
destripegui/destripe/core.py
destripegui/destripe/core_gpu.py
destripegui/destripe/raw.py
destripegui/destripe/utils.py
destripegui_gpu-2.0.0.dist-info/LICENSE.txt
destripegui_gpu-2.0.0.dist-info/METADATA
destripegui_gpu-2.0.0.dist-info/WHEEL
destripegui_gpu-2.0.0.dist-info/entry_points.txt
destripegui_gpu-2.0.0.dist-info/top_level.txt
destripegui_gpu-2.0.0.dist-info/RECORD
