Metadata-Version: 2.1
Name: destripegui-gpu
Version: 2.0.0
Summary: A GUI for automatic pystripe destriping
Home-page: https://github.com/lifecanvastechnologies
Author: LifeCanvas Technologies
License: MIT
Classifier: Development Status :: 4 - Beta
Classifier: Programming Language :: Python :: 3.11
License-File: LICENSE.txt
